README.md
setup.cfg
setup.py
easywsy/__init__.py
easywsy.egg-info/PKG-INFO
easywsy.egg-info/SOURCES.txt
easywsy.egg-info/dependency_links.txt
easywsy.egg-info/not-zip-safe
easywsy.egg-info/requires.txt
easywsy.egg-info/top_level.txt
easywsy/api/__init__.py
easywsy/api/decorators.py
easywsy/check/__init__.py
easywsy/check/mixin.py
easywsy/error/__init__.py
easywsy/error/check_error.py
easywsy/error/ws_error.py
easywsy/ws/__init__.py
easywsy/ws/web_service.py