Metadata-Version: 2.1
Name: easywsy
Version: 4.0.1
Summary: Simple Web Service development API based on suds
Home-page: https://gitlab.e-mips.com.ar/infra/easywsy
Author: Martín Nicolás Cuesta
Author-email: cuesta.martin.n@hotmail.com
Maintainer: Eynes & E-MIPS
Maintainer-email: cuesta.martin.n@hotmail.com
License: AGPL3+
Platform: UNKNOWN
Classifier: Intended Audience :: Developers
Classifier: Intended Audience :: Information Technology
Classifier: Programming Language :: Python :: 2
Classifier: Programming Language :: Python :: 3
Classifier: Operating System :: OS Independent
